pre_system/__init__.py
pre_system/additive_benchmark.py
pre_system/chaining.py
pre_system/convert.py
pre_system/formula.py
pre_system/mind4.py
pre_system/minm4.py
pre_system/multiplicative_benchmark.py
pre_system/overlay.py
pre_system/pre_system.py
pre_system/py.typed
ssb_pre_system-0.7.0.dist-info/METADATA
ssb_pre_system-0.7.0.dist-info/WHEEL
ssb_pre_system-0.7.0.dist-info/entry_points.txt
ssb_pre_system-0.7.0.dist-info/licenses/LICENSE
ssb_pre_system-0.7.0.dist-info/RECORD
