Metadata-Version: 2.4
Name: ssb-pre-system
Version: 0.7.0
Summary: Pre-system for monthly and quarterly national accounts statistics.
License-Expression: MIT
License-File: LICENSE
Author: Vemund Rundberget
Author-email: vemund.rundberget@ssb.no
Maintainer: Statistics Norway, National accounts Department (210)
Requires-Python: >=3.10,<4.0
Classifier: Development Status :: 4 - Beta
Classifier: Programming Language :: Python :: 3
Classifier: Programming Language :: Python :: 3.10
Classifier: Programming Language :: Python :: 3.11
Classifier: Programming Language :: Python :: 3.12
Classifier: Programming Language :: Python :: 3.13
Classifier: Programming Language :: Python :: 3.14
Requires-Dist: numpy (>=1.26.4)
Requires-Dist: pandas-stubs (>=2.3.2.250926)
Requires-Dist: pandas[performance] (>=2.3.3)
Requires-Dist: pyarrow (>=21.0)
Project-URL: Changelog, https://github.com/statisticsnorway/ssb-pre-system/releases
Project-URL: Documentation, https://statisticsnorway.github.io/ssb-pre-system
Project-URL: Homepage, https://github.com/statisticsnorway/ssb-pre-system
Project-URL: Repository, https://github.com/statisticsnorway/ssb-pre-system
